{
	"title": "Decisive Breakthrough",
	"comments": "",
	"url": "https://www.chess.com/daily/2011-12-31",
	"publish_time": 1325318400,
	"fen": "r2q1rk1/4bp1p/4pBp1/3pN3/3P4/pbPB3Q/1P3PPP/3RR1K1 w - - 0 1",
	"pgn": "[Date \"????.??.??\"]\r\n[Result \"*\"]\r\n[FEN \"r2q1rk1/4bp1p/4pBp1/3pN3/3P4/pbPB3Q/1P3PPP/3RR1K1 w - - 0 1\"]\r\n\r\n1. Bxg6 fxg6 2. Qxe6+ Rf7 3. Qxf7#\r\n*",
	"image": "https://www.chess.com/dynboard?fen=r2q1rk1/4bp1p/4pBp1/3pN3/3P4/pbPB3Q/1P3PPP/3RR1K1%20w%20-%20-%200%201&size=2"
}