{
	"title": "David Gurgenidze, Shakhmaty v SSSR, 1973",
	"comments": "",
	"url": "https://www.chess.com/daily/2014-06-21",
	"publish_time": 1403334000,
	"fen": "5r1k/1p1p1p2/6PP/1K1P2N1/8/r7/2P5/8 w - - 0 1",
	"pgn": "[Date \"????.??.??\"]\r\n[Result \"*\"]\r\n[FEN \"5r1k/1p1p1p2/6PP/1K1P2N1/8/r7/2P5/8 w - - 0 1\"]\r\n\r\n1. g7+ Kg8 2. Nh7 Ra5+ 3. Kb4 Ra4+ 4. Kb3 Ra3+ 5. Kb2 Ra2+ 6. Kc1 Rxc2+ 7. Kb1 Rc1+ 8. Kb2 Rc2+ 9. Kb3 Rc3+ 10. Kb4 Rc4+ 11. Kb5 Rc5+ 12. Kb6 Kxh7 13. gxf8=Q\r\n*",
	"image": "https://www.chess.com/dynboard?fen=5r1k/1p1p1p2/6PP/1K1P2N1/8/r7/2P5/8%20w%20-%20-%200%201&size=2"
}