{
	"title": "Daniel Shapiro vs Maurice Ashley, New York, 1993",
	"comments": "",
	"url": "https://www.chess.com/daily/2015-07-15",
	"publish_time": 1436943600,
	"fen": "Rr6/3kr3/5p2/2PB3p/1p3P2/1PqQP2P/6P1/6K1 w - - 0 1",
	"pgn": "[Date \"????.??.??\"]\r\n[Result \"*\"]\r\n[FEN \"Rr6/3kr3/5p2/2PB3p/1p3P2/1PqQP2P/6P1/6K1 w - - 0 1\"]\r\n\r\n1. Bc6+ Kxc6 2. Qd6+ Kb5 3. Rxb8+ Rb7 4. Rxb7+ Ka5 5. Qb6#\r\n*",
	"image": "https://www.chess.com/dynboard?fen=Rr6/3kr3/5p2/2PB3p/1p3P2/1PqQP2P/6P1/6K1%20w%20-%20-%200%201&size=2"
}