{
	"title": "Crashing the Kingside Party",
	"url": "https://www.chess.com/daily/2024-12-20",
	"publish_time": 1734681600,
	"fen": "3rr1k1/1bp2p1p/pp3Qp1/3N4/2P5/B1P5/P2q1PPP/5RK1 w - - 0 1",
	"pgn": "[White \"JohanVA\"]\r\n[Black \"Daily Puzzle Inspiration\"]\r\n[Result \"*\"]\r\n[FEN \"3rr1k1/1bp2p1p/pp3Qp1/3N4/2P5/B1P5/P2q1PPP/5RK1 w - - 0 1\"]\r\n\r\n1. Bf8 Kxf8 2. Qh8# *",
	"image": "https://www.chess.com/dynboard?fen=3rr1k1/1bp2p1p/pp3Qp1/3N4/2P5/B1P5/P2q1PPP/5RK1%20w%20-%20-%200%201&size=2"
}