{
	"title": "Keep Climbing!",
	"url": "https://www.chess.com/daily/2025-10-29",
	"publish_time": 1761721200,
	"fen": "R1r5/5pk1/2n2n2/2p1p1p1/Q1Pp4/3P2Pq/3NPP1P/2B2RK1 b - - 0 1",
	"pgn": "[White \"Daily Puzzle Inspiration\"]\r\n[Black \"technical_knockout\"]\r\n[Result \"0-1\"]\r\n[FEN \"R1r5/5pk1/2n2n2/2p1p1p1/Q1Pp4/3P2Pq/3NPP1P/2B2RK1 b - - 0 1\"]\r\n\r\n1... Ng4 2. Nf3 e4 3. dxe4 Nce5 4. Rxc8 Nxf3+ 5. exf3 Qxh2# 0-1",
	"image": "https://www.chess.com/dynboard?fen=R1r5/5pk1/2n2n2/2p1p1p1/Q1Pp4/3P2Pq/3NPP1P/2B2RK1%20b%20-%20-%200%201&size=2"
}