{
	"title": "Queenside Tilt",
	"url": "https://www.chess.com/daily/2025-08-30",
	"publish_time": 1756537200,
	"fen": "r2r2qk/p1p1p2p/1p5P/5p2/4PPn1/P3B3/1PP3Q1/2K1R2R b - - 0 1",
	"pgn": "[White \"Daily Puzzle Inspiration\"]\r\n[Black \"chesstiger787\"]\r\n[Result \"0-1\"]\r\n[FEN \"r2r2qk/p1p1p2p/1p5P/5p2/4PPn1/P3B3/1PP3Q1/2K1R2R b - - 0 1\"]\r\n\r\n1... Qa2 2. c3 Qa1+ 3. Kc2 Qd1+ 4. Rxd1 Nxe3+ 5. Kb3 Nxg2 0-1",
	"image": "https://www.chess.com/dynboard?fen=r2r2qk/p1p1p2p/1p5P/5p2/4PPn1/P3B3/1PP3Q1/2K1R2R%20b%20-%20-%200%201&size=2"
}